<?xml version="1.0"?>
<dolfin xmlns:dolfin="http://fenicsproject.org">
  <parameters name="user">
    <parameter key="c_exp" type="double" value="1.6000000000000001" />
    <parameter key="chi" type="double" value="0.40000000000000002" />
    <parameter key="eq_steps1" type="int" value="60" />
    <parameter key="eq_steps2" type="int" value="50" />
    <parameter key="gamma" type="double" value="0" />
    <parameter key="l0" type="double" value="3" />
    <parameter key="t_c_steps" type="int" value="10" />
    <parameter key="t_g_steps" type="int" value="10" />
  </parameters>
</dolfin>
